{
  "evaluation_parameters": {},
  "meta": {
    "active_batch_definition": {
      "batch_identifiers": {},
      "data_asset_name": "scraping_all_20230213",
      "data_connector_name": "all",
      "datasource_name": "glassdoor_scraping"
    },
    "batch_markers": {
      "ge_load_time": "20230302T212424.647897Z",
      "pandas_data_fingerprint": "28fa1cf2c588aa7c7c8e8434a5417d28"
    },
    "batch_spec": {
      "path": "/home/jovyan/great_expectations/../data/scraping_all_20230213.csv"
    },
    "checkpoint_id": null,
    "checkpoint_name": "checkpoint_20230213",
    "expectation_suite_name": "Main",
    "great_expectations_version": "0.15.48",
    "run_id": {
      "run_name": "20230302-212424-scraping_all_20230213",
      "run_time": "2023-03-02T21:24:24.621533+00:00"
    },
    "validation_id": null,
    "validation_time": "20230302T212424.673183Z"
  },
  "results": [
    {
      "exception_info": {
        "exception_message": null,
        "exception_traceback": null,
        "raised_exception": false
      },
      "expectation_config": {
        "expectation_type": "expect_column_values_to_not_be_null",
        "kwargs": {
          "batch_id": "a835edef57833302c353e9e1d06fbd82",
          "column": "company"
        },
        "meta": {}
      },
      "meta": {},
      "result": {
        "element_count": 450,
        "partial_unexpected_counts": [],
        "partial_unexpected_index_list": [],
        "partial_unexpected_list": [],
        "unexpected_count": 0,
        "unexpected_percent": 0.0
      },
      "success": true
    },
    {
      "exception_info": {
        "exception_message": null,
        "exception_traceback": null,
        "raised_exception": false
      },
      "expectation_config": {
        "expectation_type": "expect_column_values_to_be_in_type_list",
        "kwargs": {
          "batch_id": "a835edef57833302c353e9e1d06fbd82",
          "column": "company",
          "type_list": [
            "str"
          ]
        },
        "meta": {}
      },
      "meta": {},
      "result": {
        "element_count": 450,
        "missing_count": 0,
        "missing_percent": 0.0,
        "partial_unexpected_counts": [],
        "partial_unexpected_index_list": [],
        "partial_unexpected_list": [],
        "unexpected_count": 0,
        "unexpected_percent": 0.0,
        "unexpected_percent_nonmissing": 0.0,
        "unexpected_percent_total": 0.0
      },
      "success": true
    },
    {
      "exception_info": {
        "exception_message": null,
        "exception_traceback": null,
        "raised_exception": false
      },
      "expectation_config": {
        "expectation_type": "expect_column_values_to_match_regex",
        "kwargs": {
          "batch_id": "a835edef57833302c353e9e1d06fbd82",
          "column": "company",
          "regex": "^[A-Z].*$"
        },
        "meta": {}
      },
      "meta": {},
      "result": {
        "element_count": 450,
        "missing_count": 0,
        "missing_percent": 0.0,
        "partial_unexpected_counts": [
          {
            "count": 10,
            "value": "bestchart"
          }
        ],
        "partial_unexpected_index_list": [
          108,
          138,
          198,
          258,
          288,
          318,
          348,
          378,
          408,
          438
        ],
        "partial_unexpected_list": [
          "bestchart",
          "bestchart",
          "bestchart",
          "bestchart",
          "bestchart",
          "bestchart",
          "bestchart",
          "bestchart",
          "bestchart",
          "bestchart"
        ],
        "unexpected_count": 10,
        "unexpected_percent": 2.2222222222222223,
        "unexpected_percent_nonmissing": 2.2222222222222223,
        "unexpected_percent_total": 2.2222222222222223
      },
      "success": false
    },
    {
      "exception_info": {
        "exception_message": null,
        "exception_traceback": null,
        "raised_exception": false
      },
      "expectation_config": {
        "expectation_type": "expect_column_values_to_not_be_null",
        "kwargs": {
          "batch_id": "a835edef57833302c353e9e1d06fbd82",
          "column": "job_title"
        },
        "meta": {}
      },
      "meta": {},
      "result": {
        "element_count": 450,
        "partial_unexpected_counts": [
          {
            "count": 20,
            "value": null
          }
        ],
        "partial_unexpected_index_list": [
          106,
          108,
          116,
          136,
          138,
          146,
          196,
          198,
          206,
          256,
          258,
          266,
          286,
          288,
          296,
          316,
          318,
          326,
          346,
          348
        ],
        "partial_unexpected_list": [
          null,
          null,
          null,
          null,
          null,
          null,
          null,
          null,
          null,
          null,
          null,
          null,
          null,
          null,
          null,
          null,
          null,
          null,
          null,
          null
        ],
        "unexpected_count": 30,
        "unexpected_percent": 6.666666666666667
      },
      "success": false
    },
    {
      "exception_info": {
        "exception_message": null,
        "exception_traceback": null,
        "raised_exception": false
      },
      "expectation_config": {
        "expectation_type": "expect_column_values_to_be_in_type_list",
        "kwargs": {
          "batch_id": "a835edef57833302c353e9e1d06fbd82",
          "column": "job_title",
          "type_list": [
            "str"
          ]
        },
        "meta": {}
      },
      "meta": {},
      "result": {
        "element_count": 450,
        "missing_count": 30,
        "missing_percent": 6.666666666666667,
        "partial_unexpected_counts": [],
        "partial_unexpected_index_list": [],
        "partial_unexpected_list": [],
        "unexpected_count": 0,
        "unexpected_percent": 0.0,
        "unexpected_percent_nonmissing": 0.0,
        "unexpected_percent_total": 0.0
      },
      "success": true
    },
    {
      "exception_info": {
        "exception_message": null,
        "exception_traceback": null,
        "raised_exception": false
      },
      "expectation_config": {
        "expectation_type": "expect_column_values_to_not_be_null",
        "kwargs": {
          "batch_id": "a835edef57833302c353e9e1d06fbd82",
          "column": "location"
        },
        "meta": {}
      },
      "meta": {},
      "result": {
        "element_count": 450,
        "partial_unexpected_counts": [],
        "partial_unexpected_index_list": [],
        "partial_unexpected_list": [],
        "unexpected_count": 0,
        "unexpected_percent": 0.0
      },
      "success": true
    },
    {
      "exception_info": {
        "exception_message": null,
        "exception_traceback": null,
        "raised_exception": false
      },
      "expectation_config": {
        "expectation_type": "expect_column_values_to_be_in_type_list",
        "kwargs": {
          "batch_id": "a835edef57833302c353e9e1d06fbd82",
          "column": "location",
          "type_list": [
            "str"
          ]
        },
        "meta": {}
      },
      "meta": {},
      "result": {
        "element_count": 450,
        "missing_count": 0,
        "missing_percent": 0.0,
        "partial_unexpected_counts": [],
        "partial_unexpected_index_list": [],
        "partial_unexpected_list": [],
        "unexpected_count": 0,
        "unexpected_percent": 0.0,
        "unexpected_percent_nonmissing": 0.0,
        "unexpected_percent_total": 0.0
      },
      "success": true
    },
    {
      "exception_info": {
        "exception_message": null,
        "exception_traceback": null,
        "raised_exception": false
      },
      "expectation_config": {
        "expectation_type": "expect_column_values_to_match_regex",
        "kwargs": {
          "batch_id": "a835edef57833302c353e9e1d06fbd82",
          "column": "location",
          "regex": "^[A-Z].*$"
        },
        "meta": {}
      },
      "meta": {},
      "result": {
        "element_count": 450,
        "missing_count": 0,
        "missing_percent": 0.0,
        "partial_unexpected_counts": [],
        "partial_unexpected_index_list": [],
        "partial_unexpected_list": [],
        "unexpected_count": 0,
        "unexpected_percent": 0.0,
        "unexpected_percent_nonmissing": 0.0,
        "unexpected_percent_total": 0.0
      },
      "success": true
    },
    {
      "exception_info": {
        "exception_message": null,
        "exception_traceback": null,
        "raised_exception": false
      },
      "expectation_config": {
        "expectation_type": "expect_column_values_to_not_be_null",
        "kwargs": {
          "batch_id": "a835edef57833302c353e9e1d06fbd82",
          "column": "company_rating"
        },
        "meta": {}
      },
      "meta": {},
      "result": {
        "element_count": 450,
        "partial_unexpected_counts": [
          {
            "count": 1,
            "value": null
          },
          {
            "count": 1,
            "value": null
          },
          {
            "count": 1,
            "value": null
          },
          {
            "count": 1,
            "value": null
          },
          {
            "count": 1,
            "value": null
          },
          {
            "count": 1,
            "value": null
          },
          {
            "count": 1,
            "value": null
          },
          {
            "count": 1,
            "value": null
          },
          {
            "count": 1,
            "value": null
          },
          {
            "count": 1,
            "value": null
          },
          {
            "count": 1,
            "value": null
          },
          {
            "count": 1,
            "value": null
          },
          {
            "count": 1,
            "value": null
          },
          {
            "count": 1,
            "value": null
          },
          {
            "count": 1,
            "value": null
          },
          {
            "count": 1,
            "value": null
          },
          {
            "count": 1,
            "value": null
          },
          {
            "count": 1,
            "value": null
          },
          {
            "count": 1,
            "value": null
          },
          {
            "count": 1,
            "value": null
          }
        ],
        "partial_unexpected_index_list": [
          6,
          24,
          36,
          54,
          66,
          84,
          93,
          96,
          107,
          108,
          116,
          117,
          123,
          126,
          137,
          138,
          146,
          147,
          156,
          174
        ],
        "partial_unexpected_list": [
          null,
          null,
          null,
          null,
          null,
          null,
          null,
          null,
          null,
          null,
          null,
          null,
          null,
          null,
          null,
          null,
          null,
          null,
          null,
          null
        ],
        "unexpected_count": 70,
        "unexpected_percent": 15.555555555555555
      },
      "success": false
    },
    {
      "exception_info": {
        "exception_message": null,
        "exception_traceback": null,
        "raised_exception": false
      },
      "expectation_config": {
        "expectation_type": "expect_column_values_to_be_in_type_list",
        "kwargs": {
          "batch_id": "a835edef57833302c353e9e1d06fbd82",
          "column": "company_rating",
          "type_list": [
            "float"
          ]
        },
        "meta": {}
      },
      "meta": {},
      "result": {
        "observed_value": "float64"
      },
      "success": true
    },
    {
      "exception_info": {
        "exception_message": null,
        "exception_traceback": null,
        "raised_exception": false
      },
      "expectation_config": {
        "expectation_type": "expect_column_min_to_be_between",
        "kwargs": {
          "batch_id": "a835edef57833302c353e9e1d06fbd82",
          "column": "company_rating",
          "min_value": 0.0
        },
        "meta": {}
      },
      "meta": {},
      "result": {
        "observed_value": 2.9
      },
      "success": true
    },
    {
      "exception_info": {
        "exception_message": null,
        "exception_traceback": null,
        "raised_exception": false
      },
      "expectation_config": {
        "expectation_type": "expect_column_values_to_be_between",
        "kwargs": {
          "batch_id": "a835edef57833302c353e9e1d06fbd82",
          "column": "company_rating",
          "max_value": 5.0,
          "min_value": 0.0
        },
        "meta": {}
      },
      "meta": {},
      "result": {
        "element_count": 450,
        "missing_count": 70,
        "missing_percent": 15.555555555555555,
        "partial_unexpected_counts": [],
        "partial_unexpected_index_list": [],
        "partial_unexpected_list": [],
        "unexpected_count": 0,
        "unexpected_percent": 0.0,
        "unexpected_percent_nonmissing": 0.0,
        "unexpected_percent_total": 0.0
      },
      "success": true
    },
    {
      "exception_info": {
        "exception_message": null,
        "exception_traceback": null,
        "raised_exception": false
      },
      "expectation_config": {
        "expectation_type": "expect_column_values_to_not_be_null",
        "kwargs": {
          "batch_id": "a835edef57833302c353e9e1d06fbd82",
          "column": "job_age"
        },
        "meta": {}
      },
      "meta": {},
      "result": {
        "element_count": 450,
        "partial_unexpected_counts": [],
        "partial_unexpected_index_list": [],
        "partial_unexpected_list": [],
        "unexpected_count": 0,
        "unexpected_percent": 0.0
      },
      "success": true
    },
    {
      "exception_info": {
        "exception_message": null,
        "exception_traceback": null,
        "raised_exception": false
      },
      "expectation_config": {
        "expectation_type": "expect_column_values_to_be_in_type_list",
        "kwargs": {
          "batch_id": "a835edef57833302c353e9e1d06fbd82",
          "column": "job_age",
          "type_list": [
            "str"
          ]
        },
        "meta": {}
      },
      "meta": {},
      "result": {
        "element_count": 450,
        "missing_count": 0,
        "missing_percent": 0.0,
        "partial_unexpected_counts": [],
        "partial_unexpected_index_list": [],
        "partial_unexpected_list": [],
        "unexpected_count": 0,
        "unexpected_percent": 0.0,
        "unexpected_percent_nonmissing": 0.0,
        "unexpected_percent_total": 0.0
      },
      "success": true
    },
    {
      "exception_info": {
        "exception_message": null,
        "exception_traceback": null,
        "raised_exception": false
      },
      "expectation_config": {
        "expectation_type": "expect_column_values_to_match_regex",
        "kwargs": {
          "batch_id": "a835edef57833302c353e9e1d06fbd82",
          "column": "job_age",
          "regex": " ^\\d+\\s*(g|[dh]|day(?:s)?|\\+)?$|^Oltre\\s+\\d+\\s*g$"
        },
        "meta": {}
      },
      "meta": {},
      "result": {
        "element_count": 450,
        "missing_count": 0,
        "missing_percent": 0.0,
        "partial_unexpected_counts": [
          {
            "count": 4,
            "value": "24 h"
          },
          {
            "count": 3,
            "value": "1 giorno fa"
          },
          {
            "count": 3,
            "value": "2 g"
          },
          {
            "count": 3,
            "value": "4 g"
          },
          {
            "count": 2,
            "value": "3 g"
          },
          {
            "count": 1,
            "value": "12 g"
          },
          {
            "count": 1,
            "value": "14 g"
          },
          {
            "count": 1,
            "value": "15 g"
          },
          {
            "count": 1,
            "value": "22 g"
          },
          {
            "count": 1,
            "value": "6 g"
          }
        ],
        "partial_unexpected_index_list": [
          2,
          3,
          5,
          6,
          7,
          8,
          10,
          11,
          12,
          13,
          14,
          15,
          16,
          17,
          18,
          19,
          20,
          21,
          22,
          23
        ],
        "partial_unexpected_list": [
          "2 g",
          "4 g",
          "14 g",
          "1 giorno fa",
          "22 g",
          "3 g",
          "15 g",
          "2 g",
          "6 g",
          "1 giorno fa",
          "2 g",
          "4 g",
          "1 giorno fa",
          "4 g",
          "12 g",
          "24 h",
          "24 h",
          "3 g",
          "24 h",
          "24 h"
        ],
        "unexpected_count": 360,
        "unexpected_percent": 80.0,
        "unexpected_percent_nonmissing": 80.0,
        "unexpected_percent_total": 80.0
      },
      "success": false
    },
    {
      "exception_info": {
        "exception_message": null,
        "exception_traceback": null,
        "raised_exception": false
      },
      "expectation_config": {
        "expectation_type": "expect_column_values_to_not_be_null",
        "kwargs": {
          "batch_id": "a835edef57833302c353e9e1d06fbd82",
          "column": "job_link"
        },
        "meta": {}
      },
      "meta": {},
      "result": {
        "element_count": 450,
        "partial_unexpected_counts": [],
        "partial_unexpected_index_list": [],
        "partial_unexpected_list": [],
        "unexpected_count": 0,
        "unexpected_percent": 0.0
      },
      "success": true
    },
    {
      "exception_info": {
        "exception_message": null,
        "exception_traceback": null,
        "raised_exception": false
      },
      "expectation_config": {
        "expectation_type": "expect_column_values_to_be_in_type_list",
        "kwargs": {
          "batch_id": "a835edef57833302c353e9e1d06fbd82",
          "column": "job_link",
          "type_list": [
            "str"
          ]
        },
        "meta": {}
      },
      "meta": {},
      "result": {
        "element_count": 450,
        "missing_count": 0,
        "missing_percent": 0.0,
        "partial_unexpected_counts": [],
        "partial_unexpected_index_list": [],
        "partial_unexpected_list": [],
        "unexpected_count": 0,
        "unexpected_percent": 0.0,
        "unexpected_percent_nonmissing": 0.0,
        "unexpected_percent_total": 0.0
      },
      "success": true
    },
    {
      "exception_info": {
        "exception_message": null,
        "exception_traceback": null,
        "raised_exception": false
      },
      "expectation_config": {
        "expectation_type": "expect_column_values_to_match_regex",
        "kwargs": {
          "batch_id": "a835edef57833302c353e9e1d06fbd82",
          "column": "job_link",
          "regex": "^https://www\\.glassdoor\\.it/job-listing/.*"
        },
        "meta": {}
      },
      "meta": {},
      "result": {
        "element_count": 450,
        "missing_count": 0,
        "missing_percent": 0.0,
        "partial_unexpected_counts": [
          {
            "count": 1,
            "value": "https://www.glassdoor.it/partner/jobListing.htm?pos=1601&ao=1136043&s=58&guid=0000018631bf7068a3de97ba421af2e9&src=GD_JOB_AD&t=SR&vt=w&cs=1_820d31ff&cb=1675871876091&jobListingId=1008286277885&jrtk=3-0-1goorus4njm62801-1goorus5c20hg000-838ebbf80f6ffe3a-"
          },
          {
            "count": 1,
            "value": "https://www.glassdoor.it/partner/jobListing.htm?pos=1602&ao=1136043&s=58&guid=0000018631bf7068a3de97ba421af2e9&src=GD_JOB_AD&t=SR&vt=w&cs=1_ce31c9b1&cb=1675871876091&jobListingId=1008351503964&jrtk=3-0-1goorus4njm62801-1goorus5c20hg000-554458cb031d0119-"
          },
          {
            "count": 1,
            "value": "https://www.glassdoor.it/partner/jobListing.htm?pos=1603&ao=1136043&s=58&guid=0000018631bf7068a3de97ba421af2e9&src=GD_JOB_AD&t=SR&vt=w&cs=1_4d8273d3&cb=1675871876091&jobListingId=1008454356319&jrtk=3-0-1goorus4njm62801-1goorus5c20hg000-de9109188fa921c5-"
          },
          {
            "count": 1,
            "value": "https://www.glassdoor.it/partner/jobListing.htm?pos=1604&ao=1136043&s=58&guid=0000018631bf7068a3de97ba421af2e9&src=GD_JOB_AD&t=SR&vt=w&cs=1_91e19e4b&cb=1675871876091&jobListingId=1008450113008&jrtk=3-0-1goorus4njm62801-1goorus5c20hg000-6af1fbc6c6f38bdc-"
          },
          {
            "count": 1,
            "value": "https://www.glassdoor.it/partner/jobListing.htm?pos=1605&ao=1136043&s=58&guid=0000018631bf7068a3de97ba421af2e9&src=GD_JOB_AD&t=SR&vt=w&cs=1_bae80011&cb=1675871876092&jobListingId=1007929514706&jrtk=3-0-1goorus4njm62801-1goorus5c20hg000-d0a21e570bd38ca1-"
          },
          {
            "count": 1,
            "value": "https://www.glassdoor.it/partner/jobListing.htm?pos=1606&ao=1136043&s=58&guid=0000018631bf7068a3de97ba421af2e9&src=GD_JOB_AD&t=SR&vt=w&cs=1_ad3a3f28&cb=1675871876092&jobListingId=1008426350203&jrtk=3-0-1goorus4njm62801-1goorus5c20hg000-4609ce67473cc26e-"
          },
          {
            "count": 1,
            "value": "https://www.glassdoor.it/partner/jobListing.htm?pos=1607&ao=1136043&s=58&guid=0000018631bf7068a3de97ba421af2e9&src=GD_JOB_AD&t=SR&vt=w&ea=1&cs=1_e7692858&cb=1675871876092&jobListingId=1008454636847&jrtk=3-0-1goorus4njm62801-1goorus5c20hg000-249931a47c593035-"
          },
          {
            "count": 1,
            "value": "https://www.glassdoor.it/partner/jobListing.htm?pos=1608&ao=1136043&s=58&guid=0000018631bf7068a3de97ba421af2e9&src=GD_JOB_AD&t=SR&vt=w&cs=1_6eb3c419&cb=1675871876092&jobListingId=1008411743046&jrtk=3-0-1goorus4njm62801-1goorus5c20hg000-674ceb83ac4897f6-"
          },
          {
            "count": 1,
            "value": "https://www.glassdoor.it/partner/jobListing.htm?pos=1609&ao=1136043&s=58&guid=0000018631bf7068a3de97ba421af2e9&src=GD_JOB_AD&t=SR&vt=w&cs=1_8b12a26a&cb=1675871876092&jobListingId=1008451440245&jrtk=3-0-1goorus4njm62801-1goorus5c20hg000-511387ec2d5d2418-"
          },
          {
            "count": 1,
            "value": "https://www.glassdoor.it/partner/jobListing.htm?pos=1610&ao=1136043&s=58&guid=0000018631bf7068a3de97ba421af2e9&src=GD_JOB_AD&t=SR&vt=w&cs=1_f1d40b9a&cb=1675871876092&jobListingId=1008361132296&jrtk=3-0-1goorus4njm62801-1goorus5c20hg000-43c114ca4a4423c3-"
          },
          {
            "count": 1,
            "value": "https://www.glassdoor.it/partner/jobListing.htm?pos=1611&ao=1136043&s=58&guid=0000018631bf7068a3de97ba421af2e9&src=GD_JOB_AD&t=SR&vt=w&cs=1_eacc9aaf&cb=1675871876092&jobListingId=1008425915388&jrtk=3-0-1goorus4njm62801-1goorus5c20hg000-c0537a5e3e8f52fa-"
          },
          {
            "count": 1,
            "value": "https://www.glassdoor.it/partner/jobListing.htm?pos=1612&ao=1136043&s=58&guid=0000018631bf7068a3de97ba421af2e9&src=GD_JOB_AD&t=SR&vt=w&cs=1_4141a415&cb=1675871876092&jobListingId=1008453846774&jrtk=3-0-1goorus4njm62801-1goorus5c20hg000-3bdfd1149cc6b727-"
          },
          {
            "count": 1,
            "value": "https://www.glassdoor.it/partner/jobListing.htm?pos=1613&ao=1136043&s=58&guid=0000018631bf7068a3de97ba421af2e9&src=GD_JOB_AD&t=SR&vt=w&cs=1_3ff3755e&cb=1675871876092&jobListingId=1008444711303&jrtk=3-0-1goorus4njm62801-1goorus5c20hg000-137f95dfc3f0e1d3-"
          },
          {
            "count": 1,
            "value": "https://www.glassdoor.it/partner/jobListing.htm?pos=1614&ao=1136043&s=58&guid=0000018631bf7068a3de97ba421af2e9&src=GD_JOB_AD&t=SR&vt=w&cs=1_934acac5&cb=1675871876093&jobListingId=1008455938475&jrtk=3-0-1goorus4njm62801-1goorus5c20hg000-1b546b90a6bee747-"
          },
          {
            "count": 1,
            "value": "https://www.glassdoor.it/partner/jobListing.htm?pos=1615&ao=1136043&s=58&guid=0000018631bf7068a3de97ba421af2e9&src=GD_JOB_AD&t=SR&vt=w&cs=1_da6df83e&cb=1675871876093&jobListingId=1008454389224&jrtk=3-0-1goorus4njm62801-1goorus5c20hg000-d363668af5b2b286-"
          },
          {
            "count": 1,
            "value": "https://www.glassdoor.it/partner/jobListing.htm?pos=1616&ao=1136043&s=58&guid=0000018631bf7068a3de97ba421af2e9&src=GD_JOB_AD&t=SR&vt=w&cs=1_d2317d35&cb=1675871876093&jobListingId=1008450212466&jrtk=3-0-1goorus4njm62801-1goorus5c20hg000-a2126e3579e63f1c-"
          },
          {
            "count": 1,
            "value": "https://www.glassdoor.it/partner/jobListing.htm?pos=1617&ao=1136043&s=58&guid=0000018631bf7068a3de97ba421af2e9&src=GD_JOB_AD&t=SR&vt=w&ea=1&cs=1_0c9466da&cb=1675871876093&jobListingId=1008454637774&jrtk=3-0-1goorus4njm62801-1goorus5c20hg000-60c9c8bd5b46ae47-"
          },
          {
            "count": 1,
            "value": "https://www.glassdoor.it/partner/jobListing.htm?pos=1618&ao=1136043&s=58&guid=0000018631bf7068a3de97ba421af2e9&src=GD_JOB_AD&t=SR&vt=w&cs=1_df65693e&cb=1675871876093&jobListingId=1008450897699&jrtk=3-0-1goorus4njm62801-1goorus5c20hg000-09aabbc410407661-"
          },
          {
            "count": 1,
            "value": "https://www.glassdoor.it/partner/jobListing.htm?pos=1619&ao=1136043&s=58&guid=0000018631bf7068a3de97ba421af2e9&src=GD_JOB_AD&t=SR&vt=w&cs=1_cbb1b7ef&cb=1675871876093&jobListingId=1008433162647&jrtk=3-0-1goorus4njm62801-1goorus5c20hg000-aa0e48fd1360156a-"
          },
          {
            "count": 1,
            "value": "https://www.glassdoor.it/partner/jobListing.htm?pos=1620&ao=1136043&s=58&guid=0000018631bf7068a3de97ba421af2e9&src=GD_JOB_AD&t=SR&vt=w&cs=1_6f9afef0&cb=1675871876093&jobListingId=1008457736293&jrtk=3-0-1goorus4njm62801-1goorus5c20hg000-8a6c8f07e54abba8-"
          }
        ],
        "partial_unexpected_index_list": [
          0,
          1,
          2,
          3,
          4,
          5,
          6,
          7,
          8,
          9,
          10,
          11,
          12,
          13,
          14,
          15,
          16,
          17,
          18,
          19
        ],
        "partial_unexpected_list": [
          "https://www.glassdoor.it/partner/jobListing.htm?pos=1601&ao=1136043&s=58&guid=0000018631bf7068a3de97ba421af2e9&src=GD_JOB_AD&t=SR&vt=w&cs=1_820d31ff&cb=1675871876091&jobListingId=1008286277885&jrtk=3-0-1goorus4njm62801-1goorus5c20hg000-838ebbf80f6ffe3a-",
          "https://www.glassdoor.it/partner/jobListing.htm?pos=1602&ao=1136043&s=58&guid=0000018631bf7068a3de97ba421af2e9&src=GD_JOB_AD&t=SR&vt=w&cs=1_ce31c9b1&cb=1675871876091&jobListingId=1008351503964&jrtk=3-0-1goorus4njm62801-1goorus5c20hg000-554458cb031d0119-",
          "https://www.glassdoor.it/partner/jobListing.htm?pos=1603&ao=1136043&s=58&guid=0000018631bf7068a3de97ba421af2e9&src=GD_JOB_AD&t=SR&vt=w&cs=1_4d8273d3&cb=1675871876091&jobListingId=1008454356319&jrtk=3-0-1goorus4njm62801-1goorus5c20hg000-de9109188fa921c5-",
          "https://www.glassdoor.it/partner/jobListing.htm?pos=1604&ao=1136043&s=58&guid=0000018631bf7068a3de97ba421af2e9&src=GD_JOB_AD&t=SR&vt=w&cs=1_91e19e4b&cb=1675871876091&jobListingId=1008450113008&jrtk=3-0-1goorus4njm62801-1goorus5c20hg000-6af1fbc6c6f38bdc-",
          "https://www.glassdoor.it/partner/jobListing.htm?pos=1605&ao=1136043&s=58&guid=0000018631bf7068a3de97ba421af2e9&src=GD_JOB_AD&t=SR&vt=w&cs=1_bae80011&cb=1675871876092&jobListingId=1007929514706&jrtk=3-0-1goorus4njm62801-1goorus5c20hg000-d0a21e570bd38ca1-",
          "https://www.glassdoor.it/partner/jobListing.htm?pos=1606&ao=1136043&s=58&guid=0000018631bf7068a3de97ba421af2e9&src=GD_JOB_AD&t=SR&vt=w&cs=1_ad3a3f28&cb=1675871876092&jobListingId=1008426350203&jrtk=3-0-1goorus4njm62801-1goorus5c20hg000-4609ce67473cc26e-",
          "https://www.glassdoor.it/partner/jobListing.htm?pos=1607&ao=1136043&s=58&guid=0000018631bf7068a3de97ba421af2e9&src=GD_JOB_AD&t=SR&vt=w&ea=1&cs=1_e7692858&cb=1675871876092&jobListingId=1008454636847&jrtk=3-0-1goorus4njm62801-1goorus5c20hg000-249931a47c593035-",
          "https://www.glassdoor.it/partner/jobListing.htm?pos=1608&ao=1136043&s=58&guid=0000018631bf7068a3de97ba421af2e9&src=GD_JOB_AD&t=SR&vt=w&cs=1_6eb3c419&cb=1675871876092&jobListingId=1008411743046&jrtk=3-0-1goorus4njm62801-1goorus5c20hg000-674ceb83ac4897f6-",
          "https://www.glassdoor.it/partner/jobListing.htm?pos=1609&ao=1136043&s=58&guid=0000018631bf7068a3de97ba421af2e9&src=GD_JOB_AD&t=SR&vt=w&cs=1_8b12a26a&cb=1675871876092&jobListingId=1008451440245&jrtk=3-0-1goorus4njm62801-1goorus5c20hg000-511387ec2d5d2418-",
          "https://www.glassdoor.it/partner/jobListing.htm?pos=1610&ao=1136043&s=58&guid=0000018631bf7068a3de97ba421af2e9&src=GD_JOB_AD&t=SR&vt=w&cs=1_f1d40b9a&cb=1675871876092&jobListingId=1008361132296&jrtk=3-0-1goorus4njm62801-1goorus5c20hg000-43c114ca4a4423c3-",
          "https://www.glassdoor.it/partner/jobListing.htm?pos=1611&ao=1136043&s=58&guid=0000018631bf7068a3de97ba421af2e9&src=GD_JOB_AD&t=SR&vt=w&cs=1_eacc9aaf&cb=1675871876092&jobListingId=1008425915388&jrtk=3-0-1goorus4njm62801-1goorus5c20hg000-c0537a5e3e8f52fa-",
          "https://www.glassdoor.it/partner/jobListing.htm?pos=1612&ao=1136043&s=58&guid=0000018631bf7068a3de97ba421af2e9&src=GD_JOB_AD&t=SR&vt=w&cs=1_4141a415&cb=1675871876092&jobListingId=1008453846774&jrtk=3-0-1goorus4njm62801-1goorus5c20hg000-3bdfd1149cc6b727-",
          "https://www.glassdoor.it/partner/jobListing.htm?pos=1613&ao=1136043&s=58&guid=0000018631bf7068a3de97ba421af2e9&src=GD_JOB_AD&t=SR&vt=w&cs=1_3ff3755e&cb=1675871876092&jobListingId=1008444711303&jrtk=3-0-1goorus4njm62801-1goorus5c20hg000-137f95dfc3f0e1d3-",
          "https://www.glassdoor.it/partner/jobListing.htm?pos=1614&ao=1136043&s=58&guid=0000018631bf7068a3de97ba421af2e9&src=GD_JOB_AD&t=SR&vt=w&cs=1_934acac5&cb=1675871876093&jobListingId=1008455938475&jrtk=3-0-1goorus4njm62801-1goorus5c20hg000-1b546b90a6bee747-",
          "https://www.glassdoor.it/partner/jobListing.htm?pos=1615&ao=1136043&s=58&guid=0000018631bf7068a3de97ba421af2e9&src=GD_JOB_AD&t=SR&vt=w&cs=1_da6df83e&cb=1675871876093&jobListingId=1008454389224&jrtk=3-0-1goorus4njm62801-1goorus5c20hg000-d363668af5b2b286-",
          "https://www.glassdoor.it/partner/jobListing.htm?pos=1616&ao=1136043&s=58&guid=0000018631bf7068a3de97ba421af2e9&src=GD_JOB_AD&t=SR&vt=w&cs=1_d2317d35&cb=1675871876093&jobListingId=1008450212466&jrtk=3-0-1goorus4njm62801-1goorus5c20hg000-a2126e3579e63f1c-",
          "https://www.glassdoor.it/partner/jobListing.htm?pos=1617&ao=1136043&s=58&guid=0000018631bf7068a3de97ba421af2e9&src=GD_JOB_AD&t=SR&vt=w&ea=1&cs=1_0c9466da&cb=1675871876093&jobListingId=1008454637774&jrtk=3-0-1goorus4njm62801-1goorus5c20hg000-60c9c8bd5b46ae47-",
          "https://www.glassdoor.it/partner/jobListing.htm?pos=1618&ao=1136043&s=58&guid=0000018631bf7068a3de97ba421af2e9&src=GD_JOB_AD&t=SR&vt=w&cs=1_df65693e&cb=1675871876093&jobListingId=1008450897699&jrtk=3-0-1goorus4njm62801-1goorus5c20hg000-09aabbc410407661-",
          "https://www.glassdoor.it/partner/jobListing.htm?pos=1619&ao=1136043&s=58&guid=0000018631bf7068a3de97ba421af2e9&src=GD_JOB_AD&t=SR&vt=w&cs=1_cbb1b7ef&cb=1675871876093&jobListingId=1008433162647&jrtk=3-0-1goorus4njm62801-1goorus5c20hg000-aa0e48fd1360156a-",
          "https://www.glassdoor.it/partner/jobListing.htm?pos=1620&ao=1136043&s=58&guid=0000018631bf7068a3de97ba421af2e9&src=GD_JOB_AD&t=SR&vt=w&cs=1_6f9afef0&cb=1675871876093&jobListingId=1008457736293&jrtk=3-0-1goorus4njm62801-1goorus5c20hg000-8a6c8f07e54abba8-"
        ],
        "unexpected_count": 450,
        "unexpected_percent": 100.0,
        "unexpected_percent_nonmissing": 100.0,
        "unexpected_percent_total": 100.0
      },
      "success": false
    },
    {
      "exception_info": {
        "exception_message": null,
        "exception_traceback": null,
        "raised_exception": false
      },
      "expectation_config": {
        "expectation_type": "expect_column_values_to_not_be_null",
        "kwargs": {
          "batch_id": "a835edef57833302c353e9e1d06fbd82",
          "column": "oppurtunita_carriera"
        },
        "meta": {}
      },
      "meta": {},
      "result": {
        "element_count": 450,
        "partial_unexpected_counts": [
          {
            "count": 1,
            "value": null
          },
          {
            "count": 1,
            "value": null
          },
          {
            "count": 1,
            "value": null
          },
          {
            "count": 1,
            "value": null
          },
          {
            "count": 1,
            "value": null
          },
          {
            "count": 1,
            "value": null
          },
          {
            "count": 1,
            "value": null
          },
          {
            "count": 1,
            "value": null
          },
          {
            "count": 1,
            "value": null
          },
          {
            "count": 1,
            "value": null
          },
          {
            "count": 1,
            "value": null
          },
          {
            "count": 1,
            "value": null
          },
          {
            "count": 1,
            "value": null
          },
          {
            "count": 1,
            "value": null
          },
          {
            "count": 1,
            "value": null
          },
          {
            "count": 1,
            "value": null
          },
          {
            "count": 1,
            "value": null
          },
          {
            "count": 1,
            "value": null
          },
          {
            "count": 1,
            "value": null
          },
          {
            "count": 1,
            "value": null
          }
        ],
        "partial_unexpected_index_list": [
          0,
          3,
          4,
          6,
          7,
          11,
          13,
          14,
          15,
          16,
          17,
          18,
          19,
          20,
          21,
          22,
          23,
          25,
          26,
          27
        ],
        "partial_unexpected_list": [
          null,
          null,
          null,
          null,
          null,
          null,
          null,
          null,
          null,
          null,
          null,
          null,
          null,
          null,
          null,
          null,
          null,
          null,
          null,
          null
        ],
        "unexpected_count": 368,
        "unexpected_percent": 81.77777777777779
      },
      "success": false
    },
    {
      "exception_info": {
        "exception_message": null,
        "exception_traceback": null,
        "raised_exception": false
      },
      "expectation_config": {
        "expectation_type": "expect_column_values_to_be_in_type_list",
        "kwargs": {
          "batch_id": "a835edef57833302c353e9e1d06fbd82",
          "column": "oppurtunita_carriera",
          "type_list": [
            "float"
          ]
        },
        "meta": {}
      },
      "meta": {},
      "result": {
        "observed_value": "float64"
      },
      "success": true
    },
    {
      "exception_info": {
        "exception_message": null,
        "exception_traceback": null,
        "raised_exception": false
      },
      "expectation_config": {
        "expectation_type": "expect_column_min_to_be_between",
        "kwargs": {
          "batch_id": "a835edef57833302c353e9e1d06fbd82",
          "column": "oppurtunita_carriera",
          "min_value": 0.0
        },
        "meta": {}
      },
      "meta": {},
      "result": {
        "observed_value": 0.0
      },
      "success": true
    },
    {
      "exception_info": {
        "exception_message": null,
        "exception_traceback": null,
        "raised_exception": false
      },
      "expectation_config": {
        "expectation_type": "expect_column_values_to_be_between",
        "kwargs": {
          "batch_id": "a835edef57833302c353e9e1d06fbd82",
          "column": "oppurtunita_carriera",
          "max_value": 5.0,
          "min_value": 0.0
        },
        "meta": {}
      },
      "meta": {},
      "result": {
        "element_count": 450,
        "missing_count": 368,
        "missing_percent": 81.77777777777779,
        "partial_unexpected_counts": [],
        "partial_unexpected_index_list": [],
        "partial_unexpected_list": [],
        "unexpected_count": 0,
        "unexpected_percent": 0.0,
        "unexpected_percent_nonmissing": 0.0,
        "unexpected_percent_total": 0.0
      },
      "success": true
    },
    {
      "exception_info": {
        "exception_message": null,
        "exception_traceback": null,
        "raised_exception": false
      },
      "expectation_config": {
        "expectation_type": "expect_column_values_to_not_be_null",
        "kwargs": {
          "batch_id": "a835edef57833302c353e9e1d06fbd82",
          "column": "stipendio_e_benefit"
        },
        "meta": {}
      },
      "meta": {},
      "result": {
        "element_count": 450,
        "partial_unexpected_counts": [
          {
            "count": 1,
            "value": null
          },
          {
            "count": 1,
            "value": null
          },
          {
            "count": 1,
            "value": null
          },
          {
            "count": 1,
            "value": null
          },
          {
            "count": 1,
            "value": null
          },
          {
            "count": 1,
            "value": null
          },
          {
            "count": 1,
            "value": null
          },
          {
            "count": 1,
            "value": null
          },
          {
            "count": 1,
            "value": null
          },
          {
            "count": 1,
            "value": null
          },
          {
            "count": 1,
            "value": null
          },
          {
            "count": 1,
            "value": null
          },
          {
            "count": 1,
            "value": null
          },
          {
            "count": 1,
            "value": null
          },
          {
            "count": 1,
            "value": null
          },
          {
            "count": 1,
            "value": null
          },
          {
            "count": 1,
            "value": null
          },
          {
            "count": 1,
            "value": null
          },
          {
            "count": 1,
            "value": null
          },
          {
            "count": 1,
            "value": null
          }
        ],
        "partial_unexpected_index_list": [
          0,
          3,
          4,
          6,
          7,
          11,
          13,
          14,
          15,
          16,
          17,
          18,
          19,
          20,
          21,
          22,
          23,
          25,
          26,
          27
        ],
        "partial_unexpected_list": [
          null,
          null,
          null,
          null,
          null,
          null,
          null,
          null,
          null,
          null,
          null,
          null,
          null,
          null,
          null,
          null,
          null,
          null,
          null,
          null
        ],
        "unexpected_count": 368,
        "unexpected_percent": 81.77777777777779
      },
      "success": false
    },
    {
      "exception_info": {
        "exception_message": null,
        "exception_traceback": null,
        "raised_exception": false
      },
      "expectation_config": {
        "expectation_type": "expect_column_values_to_be_in_type_list",
        "kwargs": {
          "batch_id": "a835edef57833302c353e9e1d06fbd82",
          "column": "stipendio_e_benefit",
          "type_list": [
            "float"
          ]
        },
        "meta": {}
      },
      "meta": {},
      "result": {
        "observed_value": "float64"
      },
      "success": true
    },
    {
      "exception_info": {
        "exception_message": null,
        "exception_traceback": null,
        "raised_exception": false
      },
      "expectation_config": {
        "expectation_type": "expect_column_min_to_be_between",
        "kwargs": {
          "batch_id": "a835edef57833302c353e9e1d06fbd82",
          "column": "stipendio_e_benefit",
          "min_value": 0.0
        },
        "meta": {}
      },
      "meta": {},
      "result": {
        "observed_value": 0.0
      },
      "success": true
    },
    {
      "exception_info": {
        "exception_message": null,
        "exception_traceback": null,
        "raised_exception": false
      },
      "expectation_config": {
        "expectation_type": "expect_column_values_to_be_between",
        "kwargs": {
          "batch_id": "a835edef57833302c353e9e1d06fbd82",
          "column": "stipendio_e_benefit",
          "max_value": 5.0,
          "min_value": 0.0
        },
        "meta": {}
      },
      "meta": {},
      "result": {
        "element_count": 450,
        "missing_count": 368,
        "missing_percent": 81.77777777777779,
        "partial_unexpected_counts": [],
        "partial_unexpected_index_list": [],
        "partial_unexpected_list": [],
        "unexpected_count": 0,
        "unexpected_percent": 0.0,
        "unexpected_percent_nonmissing": 0.0,
        "unexpected_percent_total": 0.0
      },
      "success": true
    },
    {
      "exception_info": {
        "exception_message": null,
        "exception_traceback": null,
        "raised_exception": false
      },
      "expectation_config": {
        "expectation_type": "expect_column_values_to_not_be_null",
        "kwargs": {
          "batch_id": "a835edef57833302c353e9e1d06fbd82",
          "column": "cultura_e_valori"
        },
        "meta": {}
      },
      "meta": {},
      "result": {
        "element_count": 450,
        "partial_unexpected_counts": [
          {
            "count": 1,
            "value": null
          },
          {
            "count": 1,
            "value": null
          },
          {
            "count": 1,
            "value": null
          },
          {
            "count": 1,
            "value": null
          },
          {
            "count": 1,
            "value": null
          },
          {
            "count": 1,
            "value": null
          },
          {
            "count": 1,
            "value": null
          },
          {
            "count": 1,
            "value": null
          },
          {
            "count": 1,
            "value": null
          },
          {
            "count": 1,
            "value": null
          },
          {
            "count": 1,
            "value": null
          },
          {
            "count": 1,
            "value": null
          },
          {
            "count": 1,
            "value": null
          },
          {
            "count": 1,
            "value": null
          },
          {
            "count": 1,
            "value": null
          },
          {
            "count": 1,
            "value": null
          },
          {
            "count": 1,
            "value": null
          },
          {
            "count": 1,
            "value": null
          },
          {
            "count": 1,
            "value": null
          },
          {
            "count": 1,
            "value": null
          }
        ],
        "partial_unexpected_index_list": [
          0,
          3,
          4,
          6,
          7,
          11,
          13,
          14,
          15,
          16,
          17,
          18,
          19,
          20,
          21,
          22,
          23,
          25,
          26,
          27
        ],
        "partial_unexpected_list": [
          null,
          null,
          null,
          null,
          null,
          null,
          null,
          null,
          null,
          null,
          null,
          null,
          null,
          null,
          null,
          null,
          null,
          null,
          null,
          null
        ],
        "unexpected_count": 368,
        "unexpected_percent": 81.77777777777779
      },
      "success": false
    },
    {
      "exception_info": {
        "exception_message": null,
        "exception_traceback": null,
        "raised_exception": false
      },
      "expectation_config": {
        "expectation_type": "expect_column_values_to_be_in_type_list",
        "kwargs": {
          "batch_id": "a835edef57833302c353e9e1d06fbd82",
          "column": "cultura_e_valori",
          "type_list": [
            "float"
          ]
        },
        "meta": {}
      },
      "meta": {},
      "result": {
        "observed_value": "float64"
      },
      "success": true
    },
    {
      "exception_info": {
        "exception_message": null,
        "exception_traceback": null,
        "raised_exception": false
      },
      "expectation_config": {
        "expectation_type": "expect_column_min_to_be_between",
        "kwargs": {
          "batch_id": "a835edef57833302c353e9e1d06fbd82",
          "column": "cultura_e_valori",
          "min_value": 0.0
        },
        "meta": {}
      },
      "meta": {},
      "result": {
        "observed_value": 0.0
      },
      "success": true
    },
    {
      "exception_info": {
        "exception_message": null,
        "exception_traceback": null,
        "raised_exception": false
      },
      "expectation_config": {
        "expectation_type": "expect_column_values_to_be_between",
        "kwargs": {
          "batch_id": "a835edef57833302c353e9e1d06fbd82",
          "column": "cultura_e_valori",
          "max_value": 5.0,
          "min_value": 0.0
        },
        "meta": {}
      },
      "meta": {},
      "result": {
        "element_count": 450,
        "missing_count": 368,
        "missing_percent": 81.77777777777779,
        "partial_unexpected_counts": [],
        "partial_unexpected_index_list": [],
        "partial_unexpected_list": [],
        "unexpected_count": 0,
        "unexpected_percent": 0.0,
        "unexpected_percent_nonmissing": 0.0,
        "unexpected_percent_total": 0.0
      },
      "success": true
    },
    {
      "exception_info": {
        "exception_message": null,
        "exception_traceback": null,
        "raised_exception": false
      },
      "expectation_config": {
        "expectation_type": "expect_column_values_to_not_be_null",
        "kwargs": {
          "batch_id": "a835edef57833302c353e9e1d06fbd82",
          "column": "dirigenti_senior"
        },
        "meta": {}
      },
      "meta": {},
      "result": {
        "element_count": 450,
        "partial_unexpected_counts": [
          {
            "count": 1,
            "value": null
          },
          {
            "count": 1,
            "value": null
          },
          {
            "count": 1,
            "value": null
          },
          {
            "count": 1,
            "value": null
          },
          {
            "count": 1,
            "value": null
          },
          {
            "count": 1,
            "value": null
          },
          {
            "count": 1,
            "value": null
          },
          {
            "count": 1,
            "value": null
          },
          {
            "count": 1,
            "value": null
          },
          {
            "count": 1,
            "value": null
          },
          {
            "count": 1,
            "value": null
          },
          {
            "count": 1,
            "value": null
          },
          {
            "count": 1,
            "value": null
          },
          {
            "count": 1,
            "value": null
          },
          {
            "count": 1,
            "value": null
          },
          {
            "count": 1,
            "value": null
          },
          {
            "count": 1,
            "value": null
          },
          {
            "count": 1,
            "value": null
          },
          {
            "count": 1,
            "value": null
          },
          {
            "count": 1,
            "value": null
          }
        ],
        "partial_unexpected_index_list": [
          0,
          3,
          4,
          6,
          7,
          11,
          13,
          14,
          15,
          16,
          17,
          18,
          19,
          20,
          21,
          22,
          23,
          25,
          26,
          27
        ],
        "partial_unexpected_list": [
          null,
          null,
          null,
          null,
          null,
          null,
          null,
          null,
          null,
          null,
          null,
          null,
          null,
          null,
          null,
          null,
          null,
          null,
          null,
          null
        ],
        "unexpected_count": 368,
        "unexpected_percent": 81.77777777777779
      },
      "success": false
    },
    {
      "exception_info": {
        "exception_message": null,
        "exception_traceback": null,
        "raised_exception": false
      },
      "expectation_config": {
        "expectation_type": "expect_column_values_to_be_in_type_list",
        "kwargs": {
          "batch_id": "a835edef57833302c353e9e1d06fbd82",
          "column": "dirigenti_senior",
          "type_list": [
            "float"
          ]
        },
        "meta": {}
      },
      "meta": {},
      "result": {
        "observed_value": "float64"
      },
      "success": true
    },
    {
      "exception_info": {
        "exception_message": null,
        "exception_traceback": null,
        "raised_exception": false
      },
      "expectation_config": {
        "expectation_type": "expect_column_min_to_be_between",
        "kwargs": {
          "batch_id": "a835edef57833302c353e9e1d06fbd82",
          "column": "dirigenti_senior",
          "min_value": 0.0
        },
        "meta": {}
      },
      "meta": {},
      "result": {
        "observed_value": 0.0
      },
      "success": true
    },
    {
      "exception_info": {
        "exception_message": null,
        "exception_traceback": null,
        "raised_exception": false
      },
      "expectation_config": {
        "expectation_type": "expect_column_values_to_be_between",
        "kwargs": {
          "batch_id": "a835edef57833302c353e9e1d06fbd82",
          "column": "dirigenti_senior",
          "max_value": 5.0,
          "min_value": 0.0
        },
        "meta": {}
      },
      "meta": {},
      "result": {
        "element_count": 450,
        "missing_count": 368,
        "missing_percent": 81.77777777777779,
        "partial_unexpected_counts": [],
        "partial_unexpected_index_list": [],
        "partial_unexpected_list": [],
        "unexpected_count": 0,
        "unexpected_percent": 0.0,
        "unexpected_percent_nonmissing": 0.0,
        "unexpected_percent_total": 0.0
      },
      "success": true
    },
    {
      "exception_info": {
        "exception_message": null,
        "exception_traceback": null,
        "raised_exception": false
      },
      "expectation_config": {
        "expectation_type": "expect_column_values_to_not_be_null",
        "kwargs": {
          "batch_id": "a835edef57833302c353e9e1d06fbd82",
          "column": "equilibrio_lavoro_vita_privata"
        },
        "meta": {}
      },
      "meta": {},
      "result": {
        "element_count": 450,
        "partial_unexpected_counts": [
          {
            "count": 1,
            "value": null
          },
          {
            "count": 1,
            "value": null
          },
          {
            "count": 1,
            "value": null
          },
          {
            "count": 1,
            "value": null
          },
          {
            "count": 1,
            "value": null
          },
          {
            "count": 1,
            "value": null
          },
          {
            "count": 1,
            "value": null
          },
          {
            "count": 1,
            "value": null
          },
          {
            "count": 1,
            "value": null
          },
          {
            "count": 1,
            "value": null
          },
          {
            "count": 1,
            "value": null
          },
          {
            "count": 1,
            "value": null
          },
          {
            "count": 1,
            "value": null
          },
          {
            "count": 1,
            "value": null
          },
          {
            "count": 1,
            "value": null
          },
          {
            "count": 1,
            "value": null
          },
          {
            "count": 1,
            "value": null
          },
          {
            "count": 1,
            "value": null
          },
          {
            "count": 1,
            "value": null
          },
          {
            "count": 1,
            "value": null
          }
        ],
        "partial_unexpected_index_list": [
          0,
          3,
          4,
          6,
          7,
          11,
          13,
          14,
          15,
          16,
          17,
          18,
          19,
          20,
          21,
          22,
          23,
          25,
          26,
          27
        ],
        "partial_unexpected_list": [
          null,
          null,
          null,
          null,
          null,
          null,
          null,
          null,
          null,
          null,
          null,
          null,
          null,
          null,
          null,
          null,
          null,
          null,
          null,
          null
        ],
        "unexpected_count": 368,
        "unexpected_percent": 81.77777777777779
      },
      "success": false
    },
    {
      "exception_info": {
        "exception_message": null,
        "exception_traceback": null,
        "raised_exception": false
      },
      "expectation_config": {
        "expectation_type": "expect_column_values_to_be_in_type_list",
        "kwargs": {
          "batch_id": "a835edef57833302c353e9e1d06fbd82",
          "column": "equilibrio_lavoro_vita_privata",
          "type_list": [
            "float"
          ]
        },
        "meta": {}
      },
      "meta": {},
      "result": {
        "observed_value": "float64"
      },
      "success": true
    },
    {
      "exception_info": {
        "exception_message": null,
        "exception_traceback": null,
        "raised_exception": false
      },
      "expectation_config": {
        "expectation_type": "expect_column_min_to_be_between",
        "kwargs": {
          "batch_id": "a835edef57833302c353e9e1d06fbd82",
          "column": "equilibrio_lavoro_vita_privata",
          "min_value": 0.0
        },
        "meta": {}
      },
      "meta": {},
      "result": {
        "observed_value": 0.0
      },
      "success": true
    },
    {
      "exception_info": {
        "exception_message": null,
        "exception_traceback": null,
        "raised_exception": false
      },
      "expectation_config": {
        "expectation_type": "expect_column_values_to_be_between",
        "kwargs": {
          "batch_id": "a835edef57833302c353e9e1d06fbd82",
          "column": "equilibrio_lavoro_vita_privata",
          "max_value": 5.0,
          "min_value": 0.0
        },
        "meta": {}
      },
      "meta": {},
      "result": {
        "element_count": 450,
        "missing_count": 368,
        "missing_percent": 81.77777777777779,
        "partial_unexpected_counts": [],
        "partial_unexpected_index_list": [],
        "partial_unexpected_list": [],
        "unexpected_count": 0,
        "unexpected_percent": 0.0,
        "unexpected_percent_nonmissing": 0.0,
        "unexpected_percent_total": 0.0
      },
      "success": true
    },
    {
      "exception_info": {
        "exception_message": null,
        "exception_traceback": null,
        "raised_exception": false
      },
      "expectation_config": {
        "expectation_type": "expect_column_values_to_not_be_null",
        "kwargs": {
          "batch_id": "a835edef57833302c353e9e1d06fbd82",
          "column": "sede_centrale"
        },
        "meta": {}
      },
      "meta": {},
      "result": {
        "element_count": 450,
        "partial_unexpected_counts": [
          {
            "count": 20,
            "value": null
          }
        ],
        "partial_unexpected_index_list": [
          0,
          3,
          4,
          6,
          7,
          11,
          13,
          14,
          15,
          16,
          17,
          18,
          19,
          20,
          21,
          22,
          23,
          25,
          26,
          27
        ],
        "partial_unexpected_list": [
          null,
          null,
          null,
          null,
          null,
          null,
          null,
          null,
          null,
          null,
          null,
          null,
          null,
          null,
          null,
          null,
          null,
          null,
          null,
          null
        ],
        "unexpected_count": 368,
        "unexpected_percent": 81.77777777777779
      },
      "success": false
    },
    {
      "exception_info": {
        "exception_message": null,
        "exception_traceback": null,
        "raised_exception": false
      },
      "expectation_config": {
        "expectation_type": "expect_column_values_to_be_in_type_list",
        "kwargs": {
          "batch_id": "a835edef57833302c353e9e1d06fbd82",
          "column": "sede_centrale",
          "type_list": [
            "str"
          ]
        },
        "meta": {}
      },
      "meta": {},
      "result": {
        "element_count": 450,
        "missing_count": 368,
        "missing_percent": 81.77777777777779,
        "partial_unexpected_counts": [],
        "partial_unexpected_index_list": [],
        "partial_unexpected_list": [],
        "unexpected_count": 0,
        "unexpected_percent": 0.0,
        "unexpected_percent_nonmissing": 0.0,
        "unexpected_percent_total": 0.0
      },
      "success": true
    },
    {
      "exception_info": {
        "exception_message": null,
        "exception_traceback": null,
        "raised_exception": false
      },
      "expectation_config": {
        "expectation_type": "expect_column_values_to_not_be_null",
        "kwargs": {
          "batch_id": "a835edef57833302c353e9e1d06fbd82",
          "column": "dimensioni"
        },
        "meta": {}
      },
      "meta": {},
      "result": {
        "element_count": 450,
        "partial_unexpected_counts": [
          {
            "count": 20,
            "value": null
          }
        ],
        "partial_unexpected_index_list": [
          0,
          3,
          4,
          6,
          7,
          11,
          13,
          14,
          15,
          16,
          17,
          18,
          19,
          20,
          21,
          22,
          23,
          25,
          26,
          27
        ],
        "partial_unexpected_list": [
          null,
          null,
          null,
          null,
          null,
          null,
          null,
          null,
          null,
          null,
          null,
          null,
          null,
          null,
          null,
          null,
          null,
          null,
          null,
          null
        ],
        "unexpected_count": 368,
        "unexpected_percent": 81.77777777777779
      },
      "success": false
    },
    {
      "exception_info": {
        "exception_message": null,
        "exception_traceback": null,
        "raised_exception": false
      },
      "expectation_config": {
        "expectation_type": "expect_column_values_to_be_in_type_list",
        "kwargs": {
          "batch_id": "a835edef57833302c353e9e1d06fbd82",
          "column": "dimensioni",
          "type_list": [
            "str"
          ]
        },
        "meta": {}
      },
      "meta": {},
      "result": {
        "element_count": 450,
        "missing_count": 368,
        "missing_percent": 81.77777777777779,
        "partial_unexpected_counts": [],
        "partial_unexpected_index_list": [],
        "partial_unexpected_list": [],
        "unexpected_count": 0,
        "unexpected_percent": 0.0,
        "unexpected_percent_nonmissing": 0.0,
        "unexpected_percent_total": 0.0
      },
      "success": true
    },
    {
      "exception_info": {
        "exception_message": null,
        "exception_traceback": null,
        "raised_exception": false
      },
      "expectation_config": {
        "expectation_type": "expect_column_values_to_be_in_set",
        "kwargs": {
          "batch_id": "a835edef57833302c353e9e1d06fbd82",
          "column": "dimensioni",
          "value_set": [
            "Oltre 10.000 dipendenti",
            "Da 201 a 500 dipendenti",
            "Da 51 a 200 dipendenti",
            "Sconosciuto",
            "Da 1 a 50 dipendenti",
            "Da 501 a 1.000 dipendenti",
            "Da 1.001 a 5.000 dipendenti",
            "Da 5.001 a 10.000 dipendenti"
          ]
        },
        "meta": {}
      },
      "meta": {},
      "result": {
        "element_count": 450,
        "missing_count": 368,
        "missing_percent": 81.77777777777779,
        "partial_unexpected_counts": [
          {
            "count": 20,
            "value": "Non_disponibile"
          }
        ],
        "partial_unexpected_index_list": [
          2,
          5,
          8,
          9,
          10,
          24,
          41,
          43,
          64,
          73,
          78,
          79,
          84,
          92,
          94,
          95,
          101,
          110,
          115,
          121
        ],
        "partial_unexpected_list": [
          "Non_disponibile",
          "Non_disponibile",
          "Non_disponibile",
          "Non_disponibile",
          "Non_disponibile",
          "Non_disponibile",
          "Non_disponibile",
          "Non_disponibile",
          "Non_disponibile",
          "Non_disponibile",
          "Non_disponibile",
          "Non_disponibile",
          "Non_disponibile",
          "Non_disponibile",
          "Non_disponibile",
          "Non_disponibile",
          "Non_disponibile",
          "Non_disponibile",
          "Non_disponibile",
          "Non_disponibile"
        ],
        "unexpected_count": 55,
        "unexpected_percent": 67.07317073170732,
        "unexpected_percent_nonmissing": 67.07317073170732,
        "unexpected_percent_total": 12.222222222222221
      },
      "success": false
    },
    {
      "exception_info": {
        "exception_message": null,
        "exception_traceback": null,
        "raised_exception": false
      },
      "expectation_config": {
        "expectation_type": "expect_column_values_to_not_be_null",
        "kwargs": {
          "batch_id": "a835edef57833302c353e9e1d06fbd82",
          "column": "tipo"
        },
        "meta": {}
      },
      "meta": {},
      "result": {
        "element_count": 450,
        "partial_unexpected_counts": [
          {
            "count": 20,
            "value": null
          }
        ],
        "partial_unexpected_index_list": [
          0,
          3,
          4,
          6,
          7,
          11,
          13,
          14,
          15,
          16,
          17,
          18,
          19,
          20,
          21,
          22,
          23,
          25,
          26,
          27
        ],
        "partial_unexpected_list": [
          null,
          null,
          null,
          null,
          null,
          null,
          null,
          null,
          null,
          null,
          null,
          null,
          null,
          null,
          null,
          null,
          null,
          null,
          null,
          null
        ],
        "unexpected_count": 368,
        "unexpected_percent": 81.77777777777779
      },
      "success": false
    },
    {
      "exception_info": {
        "exception_message": null,
        "exception_traceback": null,
        "raised_exception": false
      },
      "expectation_config": {
        "expectation_type": "expect_column_values_to_be_in_type_list",
        "kwargs": {
          "batch_id": "a835edef57833302c353e9e1d06fbd82",
          "column": "tipo",
          "type_list": [
            "str"
          ]
        },
        "meta": {}
      },
      "meta": {},
      "result": {
        "element_count": 450,
        "missing_count": 368,
        "missing_percent": 81.77777777777779,
        "partial_unexpected_counts": [],
        "partial_unexpected_index_list": [],
        "partial_unexpected_list": [],
        "unexpected_count": 0,
        "unexpected_percent": 0.0,
        "unexpected_percent_nonmissing": 0.0,
        "unexpected_percent_total": 0.0
      },
      "success": true
    },
    {
      "exception_info": {
        "exception_message": null,
        "exception_traceback": null,
        "raised_exception": false
      },
      "expectation_config": {
        "expectation_type": "expect_column_values_to_be_in_set",
        "kwargs": {
          "batch_id": "a835edef57833302c353e9e1d06fbd82",
          "column": "tipo",
          "mostly": 0.8,
          "value_set": [
            "Azienda - Settore privato",
            "Azienda quotata in borsa"
          ]
        },
        "meta": {}
      },
      "meta": {},
      "result": {
        "element_count": 450,
        "missing_count": 368,
        "missing_percent": 81.77777777777779,
        "partial_unexpected_counts": [
          {
            "count": 15,
            "value": "Non_disponibile"
          },
          {
            "count": 4,
            "value": "Controllata o segmento aziendale"
          },
          {
            "count": 1,
            "value": "Sconosciuto"
          }
        ],
        "partial_unexpected_index_list": [
          1,
          2,
          5,
          8,
          9,
          10,
          12,
          24,
          31,
          41,
          43,
          61,
          64,
          73,
          78,
          79,
          84,
          90,
          92,
          94
        ],
        "partial_unexpected_list": [
          "Controllata o segmento aziendale",
          "Non_disponibile",
          "Non_disponibile",
          "Non_disponibile",
          "Non_disponibile",
          "Non_disponibile",
          "Controllata o segmento aziendale",
          "Non_disponibile",
          "Controllata o segmento aziendale",
          "Non_disponibile",
          "Non_disponibile",
          "Controllata o segmento aziendale",
          "Non_disponibile",
          "Non_disponibile",
          "Non_disponibile",
          "Non_disponibile",
          "Non_disponibile",
          "Sconosciuto",
          "Non_disponibile",
          "Non_disponibile"
        ],
        "unexpected_count": 70,
        "unexpected_percent": 85.36585365853658,
        "unexpected_percent_nonmissing": 85.36585365853658,
        "unexpected_percent_total": 15.555555555555555
      },
      "success": false
    },
    {
      "exception_info": {
        "exception_message": null,
        "exception_traceback": null,
        "raised_exception": false
      },
      "expectation_config": {
        "expectation_type": "expect_column_values_to_not_be_null",
        "kwargs": {
          "batch_id": "a835edef57833302c353e9e1d06fbd82",
          "column": "entrate"
        },
        "meta": {}
      },
      "meta": {},
      "result": {
        "element_count": 450,
        "partial_unexpected_counts": [
          {
            "count": 20,
            "value": null
          }
        ],
        "partial_unexpected_index_list": [
          0,
          3,
          4,
          6,
          7,
          11,
          13,
          14,
          15,
          16,
          17,
          18,
          19,
          20,
          21,
          22,
          23,
          25,
          26,
          27
        ],
        "partial_unexpected_list": [
          null,
          null,
          null,
          null,
          null,
          null,
          null,
          null,
          null,
          null,
          null,
          null,
          null,
          null,
          null,
          null,
          null,
          null,
          null,
          null
        ],
        "unexpected_count": 368,
        "unexpected_percent": 81.77777777777779
      },
      "success": false
    },
    {
      "exception_info": {
        "exception_message": null,
        "exception_traceback": null,
        "raised_exception": false
      },
      "expectation_config": {
        "expectation_type": "expect_column_values_to_be_in_type_list",
        "kwargs": {
          "batch_id": "a835edef57833302c353e9e1d06fbd82",
          "column": "entrate",
          "type_list": [
            "str"
          ]
        },
        "meta": {}
      },
      "meta": {},
      "result": {
        "element_count": 450,
        "missing_count": 368,
        "missing_percent": 81.77777777777779,
        "partial_unexpected_counts": [],
        "partial_unexpected_index_list": [],
        "partial_unexpected_list": [],
        "unexpected_count": 0,
        "unexpected_percent": 0.0,
        "unexpected_percent_nonmissing": 0.0,
        "unexpected_percent_total": 0.0
      },
      "success": true
    },
    {
      "exception_info": {
        "exception_message": null,
        "exception_traceback": null,
        "raised_exception": false
      },
      "expectation_config": {
        "expectation_type": "expect_column_values_to_be_in_set",
        "kwargs": {
          "batch_id": "a835edef57833302c353e9e1d06fbd82",
          "column": "entrate",
          "value_set": [
            "Pi\u00f9 di $ 10 miliardi (USD)",
            "$ 1 - $ 5 miliardi (USD)",
            "Sconosciuto/Non applicabile",
            "$ 100 - $ 500 milioni (USD)",
            "$ 5 - $ 25 milioni (USD)",
            "Meno di $ 1 milione (USD)",
            "$ 25 - $ 100 milioni (USD)"
          ]
        },
        "meta": {}
      },
      "meta": {},
      "result": {
        "element_count": 450,
        "missing_count": 368,
        "missing_percent": 81.77777777777779,
        "partial_unexpected_counts": [
          {
            "count": 20,
            "value": "Non_disponibile"
          }
        ],
        "partial_unexpected_index_list": [
          2,
          5,
          8,
          9,
          10,
          24,
          41,
          43,
          64,
          73,
          78,
          79,
          84,
          92,
          94,
          95,
          101,
          110,
          115,
          121
        ],
        "partial_unexpected_list": [
          "Non_disponibile",
          "Non_disponibile",
          "Non_disponibile",
          "Non_disponibile",
          "Non_disponibile",
          "Non_disponibile",
          "Non_disponibile",
          "Non_disponibile",
          "Non_disponibile",
          "Non_disponibile",
          "Non_disponibile",
          "Non_disponibile",
          "Non_disponibile",
          "Non_disponibile",
          "Non_disponibile",
          "Non_disponibile",
          "Non_disponibile",
          "Non_disponibile",
          "Non_disponibile",
          "Non_disponibile"
        ],
        "unexpected_count": 55,
        "unexpected_percent": 67.07317073170732,
        "unexpected_percent_nonmissing": 67.07317073170732,
        "unexpected_percent_total": 12.222222222222221
      },
      "success": false
    },
    {
      "exception_info": {
        "exception_message": null,
        "exception_traceback": null,
        "raised_exception": false
      },
      "expectation_config": {
        "expectation_type": "expect_column_values_to_not_be_null",
        "kwargs": {
          "batch_id": "a835edef57833302c353e9e1d06fbd82",
          "column": "fondata_nel"
        },
        "meta": {}
      },
      "meta": {},
      "result": {
        "element_count": 450,
        "partial_unexpected_counts": [],
        "partial_unexpected_index_list": [],
        "partial_unexpected_list": [],
        "unexpected_count": 0,
        "unexpected_percent": 0.0
      },
      "success": true
    },
    {
      "exception_info": {
        "exception_message": null,
        "exception_traceback": null,
        "raised_exception": false
      },
      "expectation_config": {
        "expectation_type": "expect_column_values_to_be_in_type_list",
        "kwargs": {
          "batch_id": "a835edef57833302c353e9e1d06fbd82",
          "column": "fondata_nel",
          "type_list": [
            "int"
          ]
        },
        "meta": {}
      },
      "meta": {},
      "result": {
        "observed_value": "int64"
      },
      "success": true
    },
    {
      "exception_info": {
        "exception_message": null,
        "exception_traceback": null,
        "raised_exception": false
      },
      "expectation_config": {
        "expectation_type": "expect_column_values_to_match_regex",
        "kwargs": {
          "batch_id": "a835edef57833302c353e9e1d06fbd82",
          "column": "fondata_nel",
          "regex": "[0-9]{4}"
        },
        "meta": {}
      },
      "meta": {},
      "result": {
        "element_count": 450,
        "missing_count": 0,
        "missing_percent": 0.0,
        "partial_unexpected_counts": [
          {
            "count": 20,
            "value": 0
          }
        ],
        "partial_unexpected_index_list": [
          0,
          2,
          3,
          4,
          5,
          6,
          7,
          8,
          9,
          10,
          11,
          13,
          14,
          15,
          16,
          17,
          18,
          19,
          20,
          21
        ],
        "partial_unexpected_list": [
          0,
          0,
          0,
          0,
          0,
          0,
          0,
          0,
          0,
          0,
          0,
          0,
          0,
          0,
          0,
          0,
          0,
          0,
          0,
          0
        ],
        "unexpected_count": 426,
        "unexpected_percent": 94.66666666666667,
        "unexpected_percent_nonmissing": 94.66666666666667,
        "unexpected_percent_total": 94.66666666666667
      },
      "success": false
    },
    {
      "exception_info": {
        "exception_message": null,
        "exception_traceback": null,
        "raised_exception": false
      },
      "expectation_config": {
        "expectation_type": "expect_column_min_to_be_between",
        "kwargs": {
          "batch_id": "a835edef57833302c353e9e1d06fbd82",
          "column": "fondata_nel",
          "min_value": 1000
        },
        "meta": {}
      },
      "meta": {},
      "result": {
        "observed_value": 0
      },
      "success": false
    },
    {
      "exception_info": {
        "exception_message": null,
        "exception_traceback": null,
        "raised_exception": false
      },
      "expectation_config": {
        "expectation_type": "expect_column_values_to_not_be_null",
        "kwargs": {
          "batch_id": "a835edef57833302c353e9e1d06fbd82",
          "column": "settore"
        },
        "meta": {}
      },
      "meta": {},
      "result": {
        "element_count": 450,
        "partial_unexpected_counts": [
          {
            "count": 20,
            "value": null
          }
        ],
        "partial_unexpected_index_list": [
          0,
          3,
          4,
          6,
          7,
          11,
          13,
          14,
          15,
          16,
          17,
          18,
          19,
          20,
          21,
          22,
          23,
          25,
          26,
          27
        ],
        "partial_unexpected_list": [
          null,
          null,
          null,
          null,
          null,
          null,
          null,
          null,
          null,
          null,
          null,
          null,
          null,
          null,
          null,
          null,
          null,
          null,
          null,
          null
        ],
        "unexpected_count": 368,
        "unexpected_percent": 81.77777777777779
      },
      "success": false
    },
    {
      "exception_info": {
        "exception_message": null,
        "exception_traceback": null,
        "raised_exception": false
      },
      "expectation_config": {
        "expectation_type": "expect_column_values_to_be_in_type_list",
        "kwargs": {
          "batch_id": "a835edef57833302c353e9e1d06fbd82",
          "column": "settore",
          "type_list": [
            "str"
          ]
        },
        "meta": {}
      },
      "meta": {},
      "result": {
        "element_count": 450,
        "missing_count": 368,
        "missing_percent": 81.77777777777779,
        "partial_unexpected_counts": [],
        "partial_unexpected_index_list": [],
        "partial_unexpected_list": [],
        "unexpected_count": 0,
        "unexpected_percent": 0.0,
        "unexpected_percent_nonmissing": 0.0,
        "unexpected_percent_total": 0.0
      },
      "success": true
    },
    {
      "exception_info": {
        "exception_message": null,
        "exception_traceback": null,
        "raised_exception": false
      },
      "expectation_config": {
        "expectation_type": "expect_column_values_to_not_be_null",
        "kwargs": {
          "batch_id": "a835edef57833302c353e9e1d06fbd82",
          "column": "segmento"
        },
        "meta": {}
      },
      "meta": {},
      "result": {
        "element_count": 450,
        "partial_unexpected_counts": [
          {
            "count": 20,
            "value": null
          }
        ],
        "partial_unexpected_index_list": [
          0,
          3,
          4,
          6,
          7,
          11,
          13,
          14,
          15,
          16,
          17,
          18,
          19,
          20,
          21,
          22,
          23,
          25,
          26,
          27
        ],
        "partial_unexpected_list": [
          null,
          null,
          null,
          null,
          null,
          null,
          null,
          null,
          null,
          null,
          null,
          null,
          null,
          null,
          null,
          null,
          null,
          null,
          null,
          null
        ],
        "unexpected_count": 368,
        "unexpected_percent": 81.77777777777779
      },
      "success": false
    },
    {
      "exception_info": {
        "exception_message": null,
        "exception_traceback": null,
        "raised_exception": false
      },
      "expectation_config": {
        "expectation_type": "expect_column_values_to_be_in_type_list",
        "kwargs": {
          "batch_id": "a835edef57833302c353e9e1d06fbd82",
          "column": "segmento",
          "type_list": [
            "str"
          ]
        },
        "meta": {}
      },
      "meta": {},
      "result": {
        "element_count": 450,
        "missing_count": 368,
        "missing_percent": 81.77777777777779,
        "partial_unexpected_counts": [],
        "partial_unexpected_index_list": [],
        "partial_unexpected_list": [],
        "unexpected_count": 0,
        "unexpected_percent": 0.0,
        "unexpected_percent_nonmissing": 0.0,
        "unexpected_percent_total": 0.0
      },
      "success": true
    },
    {
      "exception_info": {
        "exception_message": null,
        "exception_traceback": null,
        "raised_exception": false
      },
      "expectation_config": {
        "expectation_type": "expect_column_values_to_not_be_null",
        "kwargs": {
          "batch_id": "a835edef57833302c353e9e1d06fbd82",
          "column": "scraping_date"
        },
        "meta": {}
      },
      "meta": {},
      "result": {
        "element_count": 450,
        "partial_unexpected_counts": [],
        "partial_unexpected_index_list": [],
        "partial_unexpected_list": [],
        "unexpected_count": 0,
        "unexpected_percent": 0.0
      },
      "success": true
    },
    {
      "exception_info": {
        "exception_message": null,
        "exception_traceback": null,
        "raised_exception": false
      },
      "expectation_config": {
        "expectation_type": "expect_column_values_to_be_in_type_list",
        "kwargs": {
          "batch_id": "a835edef57833302c353e9e1d06fbd82",
          "column": "scraping_date",
          "type_list": [
            "str"
          ]
        },
        "meta": {}
      },
      "meta": {},
      "result": {
        "element_count": 450,
        "missing_count": 0,
        "missing_percent": 0.0,
        "partial_unexpected_counts": [],
        "partial_unexpected_index_list": [],
        "partial_unexpected_list": [],
        "unexpected_count": 0,
        "unexpected_percent": 0.0,
        "unexpected_percent_nonmissing": 0.0,
        "unexpected_percent_total": 0.0
      },
      "success": true
    },
    {
      "exception_info": {
        "exception_message": null,
        "exception_traceback": null,
        "raised_exception": false
      },
      "expectation_config": {
        "expectation_type": "expect_column_values_to_match_strftime_format",
        "kwargs": {
          "batch_id": "a835edef57833302c353e9e1d06fbd82",
          "column": "scraping_date",
          "strftime_format": "%Y-%m-%d"
        },
        "meta": {}
      },
      "meta": {},
      "result": {
        "element_count": 450,
        "missing_count": 0,
        "missing_percent": 0.0,
        "partial_unexpected_counts": [],
        "partial_unexpected_index_list": [],
        "partial_unexpected_list": [],
        "unexpected_count": 0,
        "unexpected_percent": 0.0,
        "unexpected_percent_nonmissing": 0.0,
        "unexpected_percent_total": 0.0
      },
      "success": true
    }
  ],
  "statistics": {
    "evaluated_expectations": 60,
    "success_percent": 65.0,
    "successful_expectations": 39,
    "unsuccessful_expectations": 21
  },
  "success": false
}